apeiron/__init__.py
apeiron/bootstrap.py
apeiron/cli.py
apeiron/config.py
apeiron/constants.py
apeiron/exceptions.py
apeiron/manifest.py
apeiron/models.py
apeiron/modpack.py
apeiron/packer.py
apeiron/view.py
apeiron-1.1.0.dist-info/AUTHORS.md
apeiron-1.1.0.dist-info/LICENSE
apeiron-1.1.0.dist-info/METADATA
apeiron-1.1.0.dist-info/WHEEL
apeiron-1.1.0.dist-info/entry_points.txt
apeiron-1.1.0.dist-info/top_level.txt
apeiron-1.1.0.dist-info/RECORD
