Metadata-Version: 2.1
Name: apeiron
Version: 1.1.0
Summary: Simple CLI for modpack management
Home-page: https://git.mc4ep.org/mc4ep/apeiron
Author: Andriy Kushnir (Orhideous)
Author-email: me@orhideous.name
License: MIT license
Keywords: Minecraft,modpack
Platform: UNKNOWN
Classifier: Development Status :: 5 - Production/Stable
Classifier: Intended Audience :: Developers
Classifier: License :: OSI Approved :: MIT License
Classifier: Natural Language :: English
Classifier: Natural Language :: Russian
Classifier: Programming Language :: Python :: 3.8
Requires-Dist: pydantic (==0.15)
Requires-Dist: PyYaml (==5.1.2)
Requires-Dist: tabulate (==0.8.6)
Requires-Dist: click (==7.0)
